prometheus_hass_sun2k/__init__.py
prometheus_hass_sun2k/cli.py
prometheus_hass_sun2k/collector.py
prometheus_hass_sun2k/config.py
prometheus_hass_sun2k/resources/config-example.yaml
prometheus_hass_sun2k/resources/systemd/prometheus-hass-sun2k.service
prometheus_hass_sun2k-0.2.0.dist-info/LICENSE
prometheus_hass_sun2k-0.2.0.dist-info/METADATA
prometheus_hass_sun2k-0.2.0.dist-info/WHEEL
prometheus_hass_sun2k-0.2.0.dist-info/entry_points.txt
prometheus_hass_sun2k-0.2.0.dist-info/RECORD
