Metadata-Version: 2.1
Name: prometheus-hass-sun2k
Version: 0.2.0
Summary: Prometheus exporter for HomeAssistant data on Huawei SUN2000 inverters
Home-page: https://pypi.org/project/prometheus-hass-sun2k/
License: MIT
Keywords: prometheus,metrics,homeassistant,sun2k,huawei,solar,solar-energy
Author: Niko Ehrenfeuchter
Author-email: mail@he1ix.org
Requires-Python: >=3.8,<4.0
Classifier: License :: OSI Approved :: MIT License
Classifier: Programming Language :: Python :: 3
Classifier: Programming Language :: Python :: 3.8
Classifier: Programming Language :: Python :: 3.9
Classifier: Programming Language :: Python :: 3.10
Classifier: Programming Language :: Python :: 3.11
Classifier: Programming Language :: Python :: 3.12
Requires-Dist: click (>=8.1.7,<9.0.0)
Requires-Dist: loguru (>=0.7.2,<0.8.0)
Requires-Dist: prometheus-client (>=0.20.0,<0.21.0)
Requires-Dist: python-box (>=7.1.1,<8.0.0)
Requires-Dist: pyyaml (>=6.0.1,<7.0.0)
Requires-Dist: requests (>=2.31.0,<3.0.0)
Project-URL: Changelog, https://github.com/ehrenfeu/prometheus-hass-sun2k/blob/main/CHANGELOG.md
Project-URL: Repository, https://github.com/ehrenfeu/prometheus-hass-sun2k
